haskellian/asyn/__init__.py
haskellian/asyn/asynch.py
haskellian/asyn/managed.py
haskellian/asyn/iterables/__init__.py
haskellian/asyn/iterables/iterables.py
haskellian/asyn/iterables/memo.py
haskellian/asyn/iterables/prefetching.py
haskellian/asyn/iterables/returning.py
haskellian/asyn/queues/__init__.py
haskellian/asyn/queues/queues.py
haskellian_async-0.1.0.dist-info/METADATA
haskellian_async-0.1.0.dist-info/WHEEL
haskellian_async-0.1.0.dist-info/top_level.txt
haskellian_async-0.1.0.dist-info/RECORD
