Metadata-Version: 2.1
Name: haskellian-async
Version: 0.1.0
Summary: FP-style tools for async code
Author-email: Marcel Claramunt <marcel@moveread.com>
Requires-Python: >=3.10
